{
  "abuzuri": "Abuzuri",
  "administratie_publica": "Administra\u0163ie public\u0103",
  "afaceri_europene_cdep": "-",
  "agricultura": "Agricultur\u0103",
  "aparare": "Ap\u0103rare",
  "buget": "Buget",
  "comunitati_de_romani": "-",
  "cultura": "Cultur\u0103",
  "drepturile_omului": "Drepturile omului",
  "economica": "Economic\u0103",
  "egalitate_sanse": "Egalitate \u015fanse",
  "industrii": "Industrii",
  "invatamant": "\u00cenv\u0103\u0163\u0103m\u00e2nt",
  "juridica": "Juridic\u0103",
  "munca": "Munc\u0103",
  "politica_externa": "Politic\u0103 extern\u0103",
  "regulament": "Regulament",
  "revolutionari": "Revolu\u0163ionari",
  "sanatate": "S\u0103n\u0103tate",
  "statut_deputati_si_senatori": "Senat",
  "tehnologia_informatiei": "Tehnologia informa\u0163iei"
}
